datta/__init__.py
datta/_attribute.py
datta/_bases.py
datta/_constants.py
datta/_data.py
datta/_dict.py
datta/_helpers.py
datta/_list.py
datta/_relationship.py
datta/_set.py
datta/exceptions.py
datta/py.typed
datta/serializers.py
datta-1.0.1.dist-info/LICENSE
datta-1.0.1.dist-info/METADATA
datta-1.0.1.dist-info/WHEEL
datta-1.0.1.dist-info/top_level.txt
datta-1.0.1.dist-info/RECORD
