Metadata-Version: 2.1
Name: datta
Version: 1.0.1
Summary: Implementation of Slotted Data Classes compatible with Python 2.7 and 3.7+.
Home-page: https://github.com/brunonicko/datta
Author: Bruno Nicko
Author-email: brunonicko@gmail.com
Classifier: Intended Audience :: Developers
Classifier: License :: OSI Approved :: MIT License
Classifier: Operating System :: OS Independent
Classifier: Programming Language :: Python :: 2.7
Classifier: Programming Language :: Python :: 3.7
Classifier: Programming Language :: Python :: 3.8
Classifier: Programming Language :: Python :: 3.9
Classifier: Programming Language :: Python :: 3.10
Classifier: Programming Language :: Python :: 3.11
Classifier: Programming Language :: Python :: Implementation :: PyPy
Requires-Python: >= 2.7, != 3.0.*, != 3.1.*, != 3.2.*, != 3.3.*, != 3.4.*, != 3.5.*, != 3.6.*
License-File: LICENSE
Requires-Dist: basicco (<9,>=8.7)
Requires-Dist: estruttura (<3,>=2)
Requires-Dist: pyrsistent (<1,>=0)
Requires-Dist: six (<2,>=1)
Requires-Dist: tippo (<4,>=3.9)
Requires-Dist: enum34 ; python_version < "3.4"
